Workbook

Sheet 1. Инструкция
B2: ИНСТРУКЦИЯ ПО ЗАПОЛНЕНИЮ ОТЧЕТА
B4: Уважаемый руководитель департамента!
B6: Вам необходимо заполнить желтые и голубые ячейки на листах 2 и 3.
B8: ЛИСТ 2 'ФАКТ VS ПРОГНОЗ':
B9: 1. Ознакомьтесь с фактом за текущий месяц.
B10: 2. В крайней правой колонке (голубой фон) напишите причину отклонения факта.
B12: ЛИСТ 3 'ОБНОВЛЕНИЕ ПРОГНОЗА':
B13: 1. Пересмотрите прогноз на будущие месяцы (до конца года).
B14: 2. Впишите новые суммы в желтые ячейки.
B15: 3. В крайней правой колонке объясните, почему прогноз изменился.
B17: ЛИСТ 4 'СВОДКА ПО ГОДУ':
B18: Здесь автоматически формируется годовой итог. Как только вы измените цифры на Листе 3, итоги на Листе 4 пересчитаются автоматически.
B20: Обратите внимание: остальные колонки защищены от редактирования.

Sheet 2. Факт vs Прогноз
A2: расход | B2: код статьи | C2: Прогноз (март) | D2: Факт (март) | E2: Отклонение (март) | F2: Отклонение % (март) | G2: Комментарий по факту
A3: Аудит | B3: 20201 | C3: 0 | D3: 0 | E3: 0 | F3: 0
A4: Банковские комиссии | B4: 20202 | C4: 5000 | D4: 4517 | E4: -483 | F4: -9.7
A5: Консультационные расходы | B5: 20203 | C5: 15000 | D5: 16095 | E5: 1095 | F5: 7.3
A6: Налоги на имущество | B6: 20205 | C6: 25000 | D6: 27258 | E6: 2258 | F6: 9
A7: Экологический сбор | B7: 20206 | C7: 3000 | D7: 2801 | E7: -199 | F7: -6.6
A8: Налог на утилизацию | B8: 20207 | C8: 4000 | D8: 3707 | E8: -293 | F8: -7.3
A9: Возмещение налогов | B9: 20208 | C9: -5000 | D9: -5341 | E9: -341 | F9: 6.8
A10: Прочие сборы | B10: 20209 | C10: 2000 | D10: 2286 | E10: 286 | F10: 14.3
A11: Аренда оборудования | B11: 20401 | C11: 25000 | D11: 0 | E11: -25000 | F11: -100
A12: Аренда земли | B12: 20402 | C12: 15000 | D12: 16403 | E12: 1403 | F12: 9.4
A13: Аренда зданий | B13: 20403 | C13: 120000 | D13: 116955 | E13: -3045 | F13: -2.5
A14: Аренда автотранспорта | B14: 20404 | C14: 35000 | D14: 35950 | E14: 950 | F14: 2.7
... A21: Амортизация транспорта | B21: 21105 | C21: 25000 | D21: 22197 | E21: -2803 | F21: -11.2

Sheet 3. Обновление прогноза
A2: расход | B2: код статьи | C2: апрель | D2: май | E2: июнь | F2: июль | G2: август | H2: сентябрь | I2: октябрь | J2: ноябрь | K2: декабрь | L2: Причина изменения прогноза
A3: Аудит | B3: 20201 | C3: 0 | D3: 0 | E3: 0 | F3: 0 | G3: 0 | H3: 0 | I3: 0 | J3: 800000 | K3: 0
A4: Банковские комиссии | B4: 20202 | C4: 5000 | D4: 5000 | E4: 5000 | F4: 5000 | G4: 5000 | H4: 5000 | I4: 5000 | J4: 5000 | K4: 5000
A5: Консультационные расходы | B5: 20203 | C5: 15000 | D5: 15000 | E5: 15000 | F5: 15000 | G5: 15000 | H5: 15000 | I5: 15000 | J5: 15000 | K5: 15000
A6: Налоги на имущество | B6: 20205 | C6: 25000 | D6: 25000 | E6: 25000 | F6: 25000 | G6: 25000 | H6: 25000 | I6: 25000 | J6: 25000 | K6: 25000
A7: Экологический сбор | B7: 20206 | C7: 3000 | D7: 3000 | E7: 3000 | F7: 3000 | G7: 3000 | H7: 3000 | I7: 3000 | J7: 3000 | K7: 3000
A8: Налог на утилизацию | B8: 20207 | C8: 4000 | D8: 4000 | E8: 4000 | F8: 4000 | G8: 4000 | H8: 4000 | I8: 4000 | J8: 4000 | K8: 4000
A9: Возмещение налогов | B9: 20208 | C9: -5000 | D9: -5000 | E9: -5000 | F9: -5000 | G9: -5000 | H9: -5000 | I9: -5000 | J9: -5000 | K9: -5000
A10: Прочие сборы | B10: 20209 | C10: 2000 | D10: 2000 | E10: 2000 | F10: 2000 | G10: 2000 | H10: 2000 | I10: 2000 | J10: 2000 | K10: 2000
A11: Аренда оборудования | B11: 20401 | C11: 25000 | D11: 25000 | E11: 25000 | F11: 25000 | G11: 25000 | H11: 25000 | I11: 25000 | J11: 25000 | K11: 25000
A12: Аренда земли | B12: 20402 | C12: 15000 | D12: 15000 | E12: 15000 | F12: 15000 | G12: 15000 | H12: 15000 | I12: 15000 | J12: 15000 | K12: 15000
A13: Аренда зданий | B13: 20403 | C13: 120000 | D13: 120000 | E13: 120000 | F13: 120000 | G13: 120000 | H13: 120000 | I13: 120000 | J13: 120000 | K13: 120000
A14: Аренда автотранспорта | B14: 20404 | C14: 35000 | D14: 35000 | E14: 35000 | F14: 35000 | G14: 35000 | H14: 35000 | I14: 35000 | J14: 35000 | K14: 35000
... A21: Амортизация транспорта | B21: 21105 | C21: 25000 | D21: 25000 | E21: 25000 | F21: 25000 | G21: 25000 | H21: 25000 | I21: 25000 | J21: 25000 | K21: 25000

Sheet 4. Сводка по году
A1: ИТОГОВАЯ СВОДКА ПО ГОДУ (с формулами)
A2: расход | B2: код статьи | C2: Бюджет (Год) | D2: Факт + Прогноз (Старый) | E2: Отклонение (Старый) | F2: Факт + Прогноз (Новый) | G2: Отклонение (Новый) | H2: Эффект от корректировки (Dif-Dif) | I2: _Факт
A3: Аудит | B3: 20201 | C3: 800000 | D3: 800000 | E3: 0 | F3: =I3 + SUM('3. Обновление прогноза'!C3:K3) | G3: =F3 - C3 | H3: =G3 - E3 | I3: 0
A4: Банковские комиссии | B4: 20202 | C4: 60000 | D4: 60188 | E4: 188 | F4: =I4 + SUM('3. Обновление прогноза'!C4:K4) | G4: =F4 - C4 | H4: =G4 - E4 | I4: 15188
A5: Консультационные расходы | B5: 20203 | C5: 180000 | D5: 182295 | E5: 2295 | F5: =I5 + SUM('3. Обновление прогноза'!C5:K5) | G5: =F5 - C5 | H5: =G5 - E5 | I5: 47295
A6: Налоги на имущество | B6: 20205 | C6: 300000 | D6: 299797 | E6: -203 | F6: =I6 + SUM('3. Обновление прогноза'!C6:K6) | G6: =F6 - C6 | H6: =G6 - E6 | I6: 74797
A7: Экологический сбор | B7: 20206 | C7: 36000 | D7: 36248 | E7: 248 | F7: =I7 + SUM('3. Обновление прогноза'!C7:K7) | G7: =F7 - C7 | H7: =G7 - E7 | I7: 9248
A8: Налог на утилизацию | B8: 20207 | C8: 48000 | D8: 48301 | E8: 301 | F8: =I8 + SUM('3. Обновление прогноза'!C8:K8) | G8: =F8 - C8 | H8: =G8 - E8 | I8: 12301
A9: Возмещение налогов | B9: 20208 | C9: -60000 | D9: -60550 | E9: -550 | F9: =I9 + SUM('3. Обновление прогноза'!C9:K9) | G9: =F9 - C9 | H9: =G9 - E9 | I9: -15550
A10: Прочие сборы | B10: 20209 | C10: 24000 | D10: 24823 | E10: 823 | F10: =I10 + SUM('3. Обновление прогноза'!C10:K10) | G10: =F10 - C10 | H10: =G10 - E10 | I10: 6823
A11: Аренда оборудования | B11: 20401 | C11: 300000 | D11: 279505 | E11: -20495 | F11: =I11 + SUM('3. Обновление прогноза'!C11:K11) | G11: =F11 - C11 | H11: =G11 - E11 | I11: 54505
A12: Аренда земли | B12: 20402 | C12: 180000 | D12: 184033 | E12: 4033 | F12: =I12 + SUM('3. Обновление прогноза'!C12:K12) | G12: =F12 - C12 | H12: =G12 - E12 | I12: 49033
A13: Аренда зданий | B13: 20403 | C13: 1440000 | D13: 1422715 | E13: -17285 | F13: =I13 + SUM('3. Обновление прогноза'!C13:K13) | G13: =F13 - C13 | H13: =G13 - E13 | I13: 342715
A14: Аренда автотранспорта | B14: 20404 | C14: 420000 | D14: 421816 | E14: 1816 | F14: =I14 + SUM('3. Обновление прогноза'!C14:K14) | G14: =F14 - C14 | H14: =G14 - E14 | I14: 106816
... A21: Амортизация транспорта | B21: 21105 | C21: 300000 | D21: 271156 | E21: -28844 | F21: =I21 + SUM('3. Обновление прогноза'!C21:K21) | G21: =F21 - C21 | H21: =G21 - E21 | I21: 46156
